talkingclock/__init__.py
talkingclock/buddha.ics
talkingclock/buddhist_holyday.py
talkingclock/soundmap.txt
talkingclock/talkingclock.py
talkingclock/mp3/0.mp3
talkingclock/mp3/1.mp3
talkingclock/mp3/10.mp3
talkingclock/mp3/11.mp3
talkingclock/mp3/12.mp3
talkingclock/mp3/13.mp3
talkingclock/mp3/14.mp3
talkingclock/mp3/15.mp3
talkingclock/mp3/16.mp3
talkingclock/mp3/17.mp3
talkingclock/mp3/18.mp3
talkingclock/mp3/19.mp3
talkingclock/mp3/1a.mp3
talkingclock/mp3/2.mp3
talkingclock/mp3/20.mp3
talkingclock/mp3/21.mp3
talkingclock/mp3/22.mp3
talkingclock/mp3/23.mp3
talkingclock/mp3/24.mp3
talkingclock/mp3/25.mp3
talkingclock/mp3/26.mp3
talkingclock/mp3/27.mp3
talkingclock/mp3/28.mp3
talkingclock/mp3/29.mp3
talkingclock/mp3/2a.mp3
talkingclock/mp3/3.mp3
talkingclock/mp3/30.mp3
talkingclock/mp3/31.mp3
talkingclock/mp3/32.mp3
talkingclock/mp3/33.mp3
talkingclock/mp3/34.mp3
talkingclock/mp3/35.mp3
talkingclock/mp3/36.mp3
talkingclock/mp3/37.mp3
talkingclock/mp3/38.mp3
talkingclock/mp3/39.mp3
talkingclock/mp3/4.mp3
talkingclock/mp3/40.mp3
talkingclock/mp3/41.mp3
talkingclock/mp3/42.mp3
talkingclock/mp3/43.mp3
talkingclock/mp3/44.mp3
talkingclock/mp3/45.mp3
talkingclock/mp3/46.mp3
talkingclock/mp3/47.mp3
talkingclock/mp3/48.mp3
talkingclock/mp3/49.mp3
talkingclock/mp3/5.mp3
talkingclock/mp3/50.mp3
talkingclock/mp3/51.mp3
talkingclock/mp3/52.mp3
talkingclock/mp3/53.mp3
talkingclock/mp3/54.mp3
talkingclock/mp3/55.mp3
talkingclock/mp3/56.mp3
talkingclock/mp3/57.mp3
talkingclock/mp3/58.mp3
talkingclock/mp3/59.mp3
talkingclock/mp3/6.mp3
talkingclock/mp3/7.mp3
talkingclock/mp3/8.mp3
talkingclock/mp3/9.mp3
talkingclock/mp3/YEAR-1.mp3
talkingclock/mp3/YEAR-10.mp3
talkingclock/mp3/YEAR-11.mp3
talkingclock/mp3/YEAR-12.mp3
talkingclock/mp3/YEAR-2.mp3
talkingclock/mp3/YEAR-3.mp3
talkingclock/mp3/YEAR-4.mp3
talkingclock/mp3/YEAR-5.mp3
talkingclock/mp3/YEAR-6.mp3
talkingclock/mp3/YEAR-7.mp3
talkingclock/mp3/YEAR-8.mp3
talkingclock/mp3/YEAR-9.mp3
talkingclock/mp3/begintime.mp3
talkingclock-1.0.dist-info/METADATA
talkingclock-1.0.dist-info/WHEEL
talkingclock-1.0.dist-info/top_level.txt
talkingclock-1.0.dist-info/RECORD
