Metadata-Version: 2.1
Name: talkingclock
Version: 1.0
Summary: A Python utility library for talking clock
Home-page: https://github.com/kcommerce/py-talkingclock
Author: Sakchart Ngamluan
Author-email: kcommerce@gmail.com
License: MIT
Classifier: Programming Language :: Python :: 3
Classifier: License :: OSI Approved :: MIT License
Classifier: Operating System :: OS Independent
Requires-Dist: playsound
Requires-Dist: icalendar
